converter/__init__.py
converter/ffmpeg.py
converter/formats.py
converter/codecs/__init__.py
converter/codecs/audio.py
converter/codecs/subtitle.py
converter/codecs/video.py
video_converter_ubicast-2.0.1.dist-info/AUTHORS.txt
video_converter_ubicast-2.0.1.dist-info/METADATA
video_converter_ubicast-2.0.1.dist-info/WHEEL
video_converter_ubicast-2.0.1.dist-info/top_level.txt
video_converter_ubicast-2.0.1.dist-info/RECORD
