Metadata-Version: 2.1
Name: video-converter-ubicast
Version: 2.0.1
Summary: Video Converter library
Home-page: https://github.com/UbiCastTeam/python-video-converter/
Author: Senko Rasic
Author-email: senko.rasic@dobarkod.hr
License-File: AUTHORS.txt
